L4/m_gen/m_gen.v
//2022-1-24
//伪随机码发生器
module m_gen (clk,
              res,
              y);
    
    input clk;
    input res;
    output y;
    
    reg [3:0] d;
    assign y = d[0];
    
    always @(posedge clk or negedge res) begin
        if (~res) begin
            d <= 4'b1111;
        end
        else begin
            d[2:0] <= d[3:1];
            d[3] = d[3] +d[0];
        end
    end
    
endmodule

L4/m_gen/m_gen_tb.v
`timescale 1ns/10ps
module m_gen_tb;
reg clk, res;

wire y;

m_gen m_gen(
    .clk(clk),
    .res(res),
    .y(y)
);
/*iverilog */
    initial
    begin
        $dumpfile("wave.vcd");        //生成的vcd文件名称
        $dumpvars(0, m_gen_tb);    //tb模块名称
    end
/*iverilog */
initial begin
        clk <= 0;
        res <= 0;
    #17 res <= 1;
    #600 $finish;
end
always #5 clk<=~clk;
endmodule

L4/m_gen/wave.vcd
$date
	Mon Jan 24 03:00:22 2022
$end
$version
	Icarus Verilog
$end
$timescale
	10ps
$end
$scope module m_gen_tb $end
$var wire 1 ! y $end
$var reg 1 " clk $end
$var reg 1 # res $end
$scope module m_gen $end
$var wire 1 " clk $end
$var wire 1 # res $end
$var wire 1 ! y $end
$var reg 4 $ d [3:0] $end
$upscope $end
$upscope $end
$enddefinitions $end
#0
$dumpvars
b1111 $
0#
0"
1!
$end
#500
1"
#1000
0"
#1500
1"
#1700
1#
#2000
0"
#2500
b111 $
1"
#3000
0"
#3500
b1011 $
1"
#4000
0"
#4500
b101 $
1"
#5000
0"
#5500
0!
b1010 $
1"
#6000
0"
#6500
1!
b1101 $
1"
#7000
0"
#7500
0!
b110 $
1"
#8000
0"
#8500
1!
b11 $
1"
#9000
0"
#9500
b1001 $
1"
#10000
0"
#10500
0!
b100 $
1"
#11000
0"
#11500
b10 $
1"
#12000
0"
#12500
1!
b1 $
1"
#13000
0"
#13500
0!
b1000 $
1"
#14000
0"
#14500
b1100 $
1"
#15000
0"
#15500
b1110 $
1"
#16000
0"
#16500
1!
b1111 $
1"
#17000
0"
#17500
b111 $
1"
#18000
0"
#18500
b1011 $
1"
#19000
0"
#19500
b101 $
1"
#20000
0"
#20500
0!
b1010 $
1"
#21000
0"
#21500
1!
b1101 $
1"
#22000
0"
#22500
0!
b110 $
1"
#23000
0"
#23500
1!
b11 $
1"
#24000
0"
#24500
b1001 $
1"
#25000
0"
#25500
0!
b100 $
1"
#26000
0"
#26500
b10 $
1"
#27000
0"
#27500
1!
b1 $
1"
#28000
0"
#28500
0!
b1000 $
1"
#29000
0"
#29500
b1100 $
1"
#30000
0"
#30500
b1110 $
1"
#31000
0"
#31500
1!
b1111 $
1"
#32000
0"
#32500
b111 $
1"
#33000
0"
#33500
b1011 $
1"
#34000
0"
#34500
b101 $
1"
#35000
0"
#35500
0!
b1010 $
1"
#36000
0"
#36500
1!
b1101 $
1"
#37000
0"
#37500
0!
b110 $
1"
#38000
0"
#38500
1!
b11 $
1"
#39000
0"
#39500
b1001 $
1"
#40000
0"
#40500
0!
b100 $
1"
#41000
0"
#41500
b10 $
1"
#42000
0"
#42500
1!
b1 $
1"
#43000
0"
#43500
0!
b1000 $
1"
#44000
0"
#44500
b1100 $
1"
#45000
0"
#45500
b1110 $
1"
#46000
0"
#46500
1!
b1111 $
1"
#47000
0"
#47500
b111 $
1"
#48000
0"
#48500
b1011 $
1"
#49000
0"
#49500
b101 $
1"
#50000
0"
#50500
0!
b1010 $
1"
#51000
0"
#51500
1!
b1101 $
1"
#52000
0"
#52500
0!
b110 $
1"
#53000
0"
#53500
1!
b11 $
1"
#54000
0"
#54500
b1001 $
1"
#55000
0"
#55500
0!
b100 $
1"
#56000
0"
#56500
b10 $
1"
#57000
0"
#57500
1!
b1 $
1"
#58000
0"
#58500
0!
b1000 $
1"
#59000
0"
#59500
b1100 $
1"
#60000
0"
#60500
b1110 $
1"
#61000
0"
#61500
1!
b1111 $
1"
