L2/fn_sw/fn_sw.v
//2022-1-12
//二选一逻辑设计
module fn_sw (a,
              b,
              sel,
              y);
    input a;
    input b;
    input sel;
    output y;
    
    // assign y = sel?(a^b):(a&b);
    //使用always语句块实现组合逻辑
    reg y;
    always @(a or b or sel)
    begin
        if (sel == 1)
        begin
            y<=a^b;
        end
        else begin
            y<=a&b;
        end    
    end
    
endmodule

L2/fn_sw/fn_sw_tb.v
`timescale 1ps/1ps
module fn_sw_tb;
reg a,b,sel;
wire y;
fn_sw fn_sw(
    .a(a),
    .b(b),
    .sel(sel),
    .y(y)
);

 /*iverilog */
    initial
    begin
        $dumpfile("wave.vcd");        //生成的vcd文件名称
        $dumpvars(0, fn_sw_tb);    //tb模块名称
    end
    /*iverilog */

initial begin
        a<=0;b<=0;sel<=0;
    #10 a<=0;b<=0;sel<=1;
    #10 a<=0;b<=1;sel<=0;
    #10 a<=0;b<=1;sel<=1;
    #10 a<=1;b<=0;sel<=0;
    #10 a<=1;b<=0;sel<=1;
    #10 a<=1;b<=1;sel<=0;
    #10 a<=1;b<=1;sel<=1;
    #10 $finish;
end

endmodule

L2/fn_sw/wave.vcd
$date
	Thu Jan 20 08:04:05 2022
$end
$version
	Icarus Verilog
$end
$timescale
	1ps
$end
$scope module fn_sw_tb $end
$var wire 1 ! y $end
$var reg 1 " a $end
$var reg 1 # b $end
$var reg 1 $ sel $end
$scope module fn_sw $end
$var wire 1 " a $end
$var wire 1 # b $end
$var wire 1 $ sel $end
$var reg 1 ! y $end
$upscope $end
$upscope $end
$enddefinitions $end
#0
$dumpvars
0$
0#
0"
0!
$end
#10
1$
#20
0$
1#
#30
1!
1$
#40
0!
0$
0#
1"
#50
1!
1$
#60
0$
1#
#70
0!
1$
