L2/fn_sw_4/fn_sw_4.v
//2022-1-20,刘澳
//四选一逻辑
module fn_sw_4(a,
               b,
               sel,
               y);
    
    input a;
    input b;
    input[1:0] sel;
    output y;
    
    reg y;
    always @(a or b or sel) begin
        case(sel)
            2'b00:begin y<=a&b; end
            2'b01:begin y<=a|b; end
            2'b10:begin y<=a^b; end
            2'b11:begin y<=~(a^b); end
        endcase
    end
endmodule

L2/fn_sw_4/fn_sw_4_tb.v
`timescale 1ps/1ps
module fn_sw_4_tb; 
    reg[3:0] absel; 
    wire y;
    fn_sw_4 fn_sw_4(
        .a(absel[0]), 
        .b(absel[1]), 
        .sel(absel[3:2]), 
        .y(y)
        );
    /*iverilog */
    initial
    begin
        $dumpfile("wave.vcd");        //生成的vcd文件名称
        $dumpvars(0, fn_sw_4_tb);    //tb模块名称
    end
    /*iverilog */
    initial begin
            absel<=0;
        #200 $finish;
    end

    always #10 absel<=absel+1;

endmodule

L2/fn_sw_4/wave.vcd
$date
	Thu Jan 20 10:37:16 2022
$end
$version
	Icarus Verilog
$end
$timescale
	1ps
$end
$scope module fn_sw_4_tb $end
$var wire 1 ! y $end
$var reg 4 " absel [3:0] $end
$scope module fn_sw_4 $end
$var wire 1 # a $end
$var wire 1 $ b $end
$var wire 2 % sel [1:0] $end
$var reg 1 ! y $end
$upscope $end
$upscope $end
$enddefinitions $end
#0
$dumpvars
b0 %
0$
0#
b0 "
0!
$end
#10
1#
b1 "
#20
0#
1$
b10 "
#30
1!
1#
b11 "
#40
0!
0#
0$
b1 %
b100 "
#50
1!
1#
b101 "
#60
0#
1$
b110 "
#70
1#
b111 "
#80
0!
0#
0$
b10 %
b1000 "
#90
1!
1#
b1001 "
#100
0#
1$
b1010 "
#110
0!
1#
b1011 "
#120
1!
0#
0$
b11 %
b1100 "
#130
0!
1#
b1101 "
#140
0#
1$
b1110 "
#150
1!
1#
b1111 "
#160
0!
0#
0$
b0 %
b0 "
#170
1#
b1 "
#180
0#
1$
b10 "
#190
1!
1#
b11 "
#200
0!
0#
0$
b1 %
b100 "
