L3/seg_dec/seg_dec.v
//2022-1-24
module seg_dec (num,
                a_g);
    input[3:0] num;
    output[6:0] a_g;
    
    reg[6:0] a_g;
    always @(num) begin
        case (num)
            4'd0: begin a_g <= 7'b111_1110; end
            4'd1: begin a_g <= 7'b011_0000; end
            4'd2: begin a_g <= 7'b110_1101; end
            4'd3: begin a_g <= 7'b111_1110; end
            4'd4: begin a_g <= 7'b011_0011; end
            4'd5: begin a_g <= 7'b101_1011; end
            4'd6: begin a_g <= 7'b101_1111; end
            4'd7: begin a_g <= 7'b111_0000; end
            4'd8: begin a_g <= 7'b111_1111; end
            4'd9: begin a_g <= 7'b111_1011; end
            default: begin a_g <= 7'b000_0001; end
        endcase
    end   
endmodule

L3/seg_dec/seg_dec_tb.v
`timescale 1ps/1ps
module seg_dec_tb;
reg [3:0] a_in;
wire [6:0] y_out;

seg_dec seg_dec(
    .num(a_in),
    .a_g(y_out)
);

/*iverilog */
    initial
    begin
        $dumpfile("wave.vcd");        //生成的vcd文件名称
        $dumpvars(0, seg_dec_tb);    //tb模块名称
    end
/*iverilog */

initial begin
        a_in<=0;
    #128 $finish;
end
always #10 a_in<=a_in+1;

endmodule

L3/seg_dec/wave.vcd
$date
	Mon Jan 24 01:36:02 2022
$end
$version
	Icarus Verilog
$end
$timescale
	1ps
$end
$scope module seg_dec_tb $end
$var wire 7 ! y_out [6:0] $end
$var reg 4 " a_in [3:0] $end
$scope module seg_dec $end
$var wire 4 # num [3:0] $end
$var reg 7 $ a_g [6:0] $end
$upscope $end
$upscope $end
$enddefinitions $end
#0
$dumpvars
b1111110 $
b0 #
b0 "
b1111110 !
$end
#10
b110000 !
b110000 $
b1 "
b1 #
#20
b1101101 !
b1101101 $
b10 "
b10 #
#30
b1111110 !
b1111110 $
b11 "
b11 #
#40
b110011 !
b110011 $
b100 "
b100 #
#50
b1011011 !
b1011011 $
b101 "
b101 #
#60
b1011111 !
b1011111 $
b110 "
b110 #
#70
b1110000 !
b1110000 $
b111 "
b111 #
#80
b1111111 !
b1111111 $
b1000 "
b1000 #
#90
b1111011 !
b1111011 $
b1001 "
b1001 #
#100
b1 !
b1 $
b1010 "
b1010 #
#110
b1011 "
b1011 #
#120
b1100 "
b1100 #
